pyarccore/__init__.py
pyarccore/config_manager.py
pyarccore/feature_manager.py
pyarccore/internationalisation_manager.py
pyarccore/page_manager.py
pyarccore/request_utils.py
pyarccore/router.py
pyarccore/versionning.py
pyarccore-0.0.1211147.dist-info/LICENSE
pyarccore-0.0.1211147.dist-info/METADATA
pyarccore-0.0.1211147.dist-info/WHEEL
pyarccore-0.0.1211147.dist-info/top_level.txt
pyarccore-0.0.1211147.dist-info/RECORD
