Metadata-Version: 2.1
Name: pyarccore
Version: 0.0.1211147
Summary: Paquetage Python pour gérer les configurations, l'internationalisation et les routes dans les applications FastAPI
Home-page: https://github.com/inicode_celestin03/pyarccore
Author: INICODE
Author-email: contact.inicode@gmail.com
License: UNKNOWN
Platform: UNKNOWN
Classifier: Programming Language :: Python :: 3
Classifier: License :: OSI Approved :: MIT License
Classifier: Operating System :: OS Independent
Requires-Python: >=3.7
License-File: LICENSE
Requires-Dist: fastapi (>=0.68.0)
Requires-Dist: python-multipart (>=0.0.5)
Requires-Dist: uvicorn (>=0.15.0)
